{"zhenyulei":[{"proName":"PLUS省钱商品触达【四期】_增加悬浮按钮和联名卡配置化","proBg":"","proPlan":"","proProgress":"因产品需求改动，省钱攻略页浮层根据新的投放接口判断展示,整体进度60%，已提测，预计25号上线","proProblem":"","proWork":"","proId":"1589972251658","proPerson":"叶文文","proErp":"zhenyulei"},{"proName":"文章撰写","proBg":"","proPlan":"","proProgress":"","proProblem":"","proWork":"1.《NutUI造轮子之视频Video组件文章撰写》完成组件实现和使用部分的撰写，整体进度60%\n2.《Legao项目zIndex层级管理解析》滚动穿透原因和解决方案，整理出现的情况的素材和两种解决方式，进度80%；","proId":"1589972551185","proPerson":"叶文文/杨凯旋","proErp":"zhenyulei"},{"proName":"PC端惠购年卡需求","proBg":"","proPlan":"","proProgress":"开发已经完成，今晚提测 整体进度30%","proProblem":"","proWork":"","proId":"1589972596838","proPerson":"甄玉磊","proErp":"zhenyulei"},{"proName":"正式中改版v2.0","proBg":"","proPlan":"","proProgress":"进度  二期，数据交互开发中，开发进度70%。","proProblem":"","proWork":"1、专属优惠券楼层点击和曝光埋点开发完成。\n2、95折feeds楼层数据交互（无限加载，加载出错、已到底等状态）和埋点（点击和曝光）开发完成。 \n3、95折父楼层和子楼层做ios屏蔽处理。","proId":"1589972727576","proPerson":"甄玉磊","proErp":"zhenyulei"},{"proName":"小组日报系统开发","proBg":"","proPlan":"","proProgress":"","proProblem":"今天部署到了服务器上，并且实现了https证书的安装，以及PWA中manifest的功能，这样可以安装成桌面应用，在下午最后时刻突然想起来，如果修改公共json文件的话，我每次提交代码都会覆盖当前的json，导致成员保存的内容消失，所以暂时想到的是在服务器项目外面新建公共的json文件来保存日报，目前正在调试中。","proWork":"","proId":"1589972757485","proPerson":"甄玉磊","proErp":"zhenyulei"},{"proName":"plus需求日常维护","proBg":"","proPlan":"","proProgress":"","proProblem":"","proWork":"1.  昨晚11点多，测试产品找到我，线上商品楼层的品牌95折无法加载出来，初步判断为是返回数据问题，但是没有带电脑无法验证调试，今天一早和凯旋文文一起核对了一下，确实是他们数据问题，有些字段没有数据，已经反馈给前台修改；\n2.咱们多个同事反馈进入plus权益详情页白屏，配合石汀露团队排查问题，发现返回html页面，但是没有请求静态资源，和咱们首页当时的情况很类似，之后突然就又可以打开了，下午测试陆续反馈有人权益详情页无法打开，目前石汀露团队还在跟进；\n3.预发A环境，百宝箱QQ权益卡没有调相应接口，凯旋跟进，发现是预发A静态资源不对，重新推送。","proId":"1589972894520","proPerson":"甄玉磊/杨凯旋","proErp":"zhenyulei"}]}